Topsis/__init__.py
Topsis/__main__.py
Topsis_Jasrehmat_102103146-1.0.0.dist-info/METADATA
Topsis_Jasrehmat_102103146-1.0.0.dist-info/WHEEL
Topsis_Jasrehmat_102103146-1.0.0.dist-info/entry_points.txt
Topsis_Jasrehmat_102103146-1.0.0.dist-info/top_level.txt
Topsis_Jasrehmat_102103146-1.0.0.dist-info/RECORD
