Metadata-Version: 2.1
Name: Topsis-Jasrehmat-102103146
Version: 1.0.0
Summary: Gives the TOPSIS score and rank for your data
Author: Jasrehmat Kaur
Author-email: jasrehmat2003@gmail.com
License: MIT
Classifier: License :: OSI Approved :: MIT License
Classifier: Programming Language :: Python :: 3.6
Classifier: Programming Language :: Python :: 3.7
Classifier: Programming Language :: Python :: 3.8
